CHANGELOG.md
hackrf/__init__.py
pyhackrf-0.2.0.dist-info/COPYING
pyhackrf-0.2.0.dist-info/WHEEL
pyhackrf-0.2.0.dist-info/METADATA
pyhackrf-0.2.0.dist-info/RECORD
