Metadata-Version: 2.1
Name: pyhackrf
Version: 0.2.0
Summary: Python wrapper for the libhackrf library
License: GPL-3
Author: 4thel00z
Author-email: 4thel00z@gmail.com
Requires-Python: >=3.9,<4.0
Classifier: License :: Other/Proprietary License
Classifier: Programming Language :: Python :: 3
Classifier: Programming Language :: Python :: 3.9
Requires-Dist: numpy (>=1.20.3,<2.0.0)
